podcastake-0.1.1.dist-info/metadata.json
podcastake-0.1.1.dist-info/METADATA
podcastake-0.1.1.dist-info/WHEEL
podcastake-0.1.1.dist-info/entry_points.txt
podcastake-0.1.1.dist-info/top_level.txt
podcastake-0.1.1.dist-info/zip-safe
podcastake-0.1.1.dist-info/DESCRIPTION.rst
podcastake-0.1.1.dist-info/RECORD
podcastake/podcast.py
podcastake/__init__.py
