Metadata-Version: 2.0
Name: podcastake
Version: 0.1.1
Summary: download post cast according to the entry url
Home-page: https://github.com/etng/podcastake
Author: y10n
Author-email: etng2004@gmail.com
License: MIT
Keywords: python podcast download terminal
Platform: UNKNOWN
Requires-Dist: requests
